client_bank_1c.py
client_bank_1c-0.3.dist-info/LICENSE
client_bank_1c-0.3.dist-info/METADATA
client_bank_1c-0.3.dist-info/WHEEL
client_bank_1c-0.3.dist-info/RECORD
